{
  "analysis_date": "2026-02-20 00:48:34",
  "strategy": "Insider Conviction (No Hindsight)",
  "overall_stats": {
    "stocks_analyzed": 1,
    "total_trades": 2,
    "winning_trades": 2,
    "overall_win_rate": 100.0,
    "total_profit": 8580.08,
    "total_invested": 4000,
    "overall_roi": 214.5
  },
  "top_25_best": [
    {
      "ticker": "BLNE",
      "company_name": "X",
      "total_trades": 4,
      "winning_trades": 3,
      "losing_trades": 1,
      "win_rate": 75.0,
      "target_rate": 50.0,
      "total_profit": 8284.06,
      "total_invested": 8000,
      "roi": 103.55,
      "avg_return": 103.55,
      "median_return": 66.67,
      "max_return": 362.34,
      "min_return": -15.89,
      "avg_days_held": 56.2,
      "trades": [
        {
          "entry_date": "2022-07-18",
          "entry_price": 128.4,
          "exit_date": "2022-08-18",
          "exit_price": 108.0,
          "target_price": 195.4,
          "days_held": 31,
          "return_pct": -15.89,
          "position_size": 2000,
          "profit_loss": -317.76,
          "sell_reason": "stop_loss",
          "target_reached": "no",
          "peak_gain": 12.15,
          "buy_type": "shopping_spree"
        },
        {
          "entry_date": "2025-02-06",
          "entry_price": 7.36,
          "exit_date": "2025-02-25",
          "exit_price": 7.44,
          "target_price": 7.88,
          "days_held": 19,
          "return_pct": 1.09,
          "position_size": 2000,
          "profit_loss": 21.74,
          "sell_reason": "target_reached_first_dip",
          "target_reached": "yes",
          "peak_gain": 11.41,
          "buy_type": "shopping_spree"
        },
        {
          "entry_date": "2025-06-18",
          "entry_price": 0.77,
          "exit_date": "2025-09-17",
          "exit_price": 3.56,
          "target_price": 2.9,
          "days_held": 91,
          "return_pct": 362.34,
          "position_size": 2000,
          "profit_loss": 7246.75,
          "sell_reason": "target_reached_first_dip",
          "target_reached": "yes",
          "peak_gain": 402.6,
          "buy_type": "shopping_spree"
        },
        {
          "entry_date": "2025-11-25",
          "entry_price": 1.77,
          "exit_date": "2026-02-17",
          "exit_price": 2.95,
          "target_price": 4.35,
          "days_held": 84,
          "return_pct": 66.67,
          "position_size": 2000,
          "profit_loss": 1333.33,
          "sell_reason": "end_of_period",
          "target_reached": "no",
          "peak_gain": 102.82,
          "buy_type": "shopping_spree"
        }
      ]
    }
  ],
  "top_25_worst": [
    {
      "ticker": "BLNE",
      "company_name": "X",
      "total_trades": 4,
      "winning_trades": 3,
      "losing_trades": 1,
      "win_rate": 75.0,
      "target_rate": 50.0,
      "total_profit": 8284.06,
      "total_invested": 8000,
      "roi": 103.55,
      "avg_return": 103.55,
      "median_return": 66.67,
      "max_return": 362.34,
      "min_return": -15.89,
      "avg_days_held": 56.2,
      "trades": [
        {
          "entry_date": "2022-07-18",
          "entry_price": 128.4,
          "exit_date": "2022-08-18",
          "exit_price": 108.0,
          "target_price": 195.4,
          "days_held": 31,
          "return_pct": -15.89,
          "position_size": 2000,
          "profit_loss": -317.76,
          "sell_reason": "stop_loss",
          "target_reached": "no",
          "peak_gain": 12.15,
          "buy_type": "shopping_spree"
        },
        {
          "entry_date": "2025-02-06",
          "entry_price": 7.36,
          "exit_date": "2025-02-25",
          "exit_price": 7.44,
          "target_price": 7.88,
          "days_held": 19,
          "return_pct": 1.09,
          "position_size": 2000,
          "profit_loss": 21.74,
          "sell_reason": "target_reached_first_dip",
          "target_reached": "yes",
          "peak_gain": 11.41,
          "buy_type": "shopping_spree"
        },
        {
          "entry_date": "2025-06-18",
          "entry_price": 0.77,
          "exit_date": "2025-09-17",
          "exit_price": 3.56,
          "target_price": 2.9,
          "days_held": 91,
          "return_pct": 362.34,
          "position_size": 2000,
          "profit_loss": 7246.75,
          "sell_reason": "target_reached_first_dip",
          "target_reached": "yes",
          "peak_gain": 402.6,
          "buy_type": "shopping_spree"
        },
        {
          "entry_date": "2025-11-25",
          "entry_price": 1.77,
          "exit_date": "2026-02-17",
          "exit_price": 2.95,
          "target_price": 4.35,
          "days_held": 84,
          "return_pct": 66.67,
          "position_size": 2000,
          "profit_loss": 1333.33,
          "sell_reason": "end_of_period",
          "target_reached": "no",
          "peak_gain": 102.82,
          "buy_type": "shopping_spree"
        }
      ]
    }
  ],
  "all_results": [
    {
      "ticker": "BLNE",
      "company_name": "X",
      "total_trades": 4,
      "winning_trades": 3,
      "losing_trades": 1,
      "win_rate": 75.0,
      "target_rate": 50.0,
      "total_profit": 8284.06,
      "total_invested": 8000,
      "roi": 103.55,
      "avg_return": 103.55,
      "median_return": 66.67,
      "max_return": 362.34,
      "min_return": -15.89,
      "avg_days_held": 56.2,
      "trades": [
        {
          "entry_date": "2022-07-18",
          "entry_price": 128.4,
          "exit_date": "2022-08-18",
          "exit_price": 108.0,
          "target_price": 195.4,
          "days_held": 31,
          "return_pct": -15.89,
          "position_size": 2000,
          "profit_loss": -317.76,
          "sell_reason": "stop_loss",
          "target_reached": "no",
          "peak_gain": 12.15,
          "buy_type": "shopping_spree"
        },
        {
          "entry_date": "2025-02-06",
          "entry_price": 7.36,
          "exit_date": "2025-02-25",
          "exit_price": 7.44,
          "target_price": 7.88,
          "days_held": 19,
          "return_pct": 1.09,
          "position_size": 2000,
          "profit_loss": 21.74,
          "sell_reason": "target_reached_first_dip",
          "target_reached": "yes",
          "peak_gain": 11.41,
          "buy_type": "shopping_spree"
        },
        {
          "entry_date": "2025-06-18",
          "entry_price": 0.77,
          "exit_date": "2025-09-17",
          "exit_price": 3.56,
          "target_price": 2.9,
          "days_held": 91,
          "return_pct": 362.34,
          "position_size": 2000,
          "profit_loss": 7246.75,
          "sell_reason": "target_reached_first_dip",
          "target_reached": "yes",
          "peak_gain": 402.6,
          "buy_type": "shopping_spree"
        },
        {
          "entry_date": "2025-11-25",
          "entry_price": 1.77,
          "exit_date": "2026-02-17",
          "exit_price": 2.95,
          "target_price": 4.35,
          "days_held": 84,
          "return_pct": 66.67,
          "position_size": 2000,
          "profit_loss": 1333.33,
          "sell_reason": "end_of_period",
          "target_reached": "no",
          "peak_gain": 102.82,
          "buy_type": "shopping_spree"
        }
      ]
    },
    {
      "ticker": "SEZL",
      "company_name": "X",
      "total_trades": 2,
      "winning_trades": 1,
      "losing_trades": 1,
      "win_rate": 50.0,
      "target_rate": 50.0,
      "total_profit": 325.86,
      "total_invested": 4000,
      "roi": 8.15,
      "avg_return": 8.15,
      "median_return": 34.26,
      "max_return": 34.26,
      "min_return": -17.96,
      "avg_days_held": 14.5,
      "trades": [
        {
          "entry_date": "2025-01-03",
          "entry_price": 46.45,
          "exit_date": "2025-01-10",
          "exit_price": 38.1,
          "target_price": 65.02,
          "days_held": 7,
          "return_pct": -17.96,
          "position_size": 2000,
          "profit_loss": -359.25,
          "sell_reason": "stop_loss",
          "target_reached": "no",
          "peak_gain": 0,
          "buy_type": "shopping_spree"
        },
        {
          "entry_date": "2025-11-20",
          "entry_price": 52.4,
          "exit_date": "2025-12-12",
          "exit_price": 70.35,
          "target_price": 70.1,
          "days_held": 22,
          "return_pct": 34.26,
          "position_size": 2000,
          "profit_loss": 685.11,
          "sell_reason": "absorption_target_reached",
          "target_reached": "yes",
          "peak_gain": 40.94,
          "buy_type": "absorption_buy"
        }
      ]
    }
  ]
}